ccm_analysis_pynb/__init__.py
ccm_analysis_pynb/analysis.py
ccm_analysis_pynb-1.13.0.dist-info/METADATA
ccm_analysis_pynb-1.13.0.dist-info/WHEEL
ccm_analysis_pynb-1.13.0.dist-info/top_level.txt
ccm_analysis_pynb-1.13.0.dist-info/RECORD
